cameo_txt/__init__.py
cameo_txt-0.0.1.dist-info/LICENSE
cameo_txt-0.0.1.dist-info/METADATA
cameo_txt-0.0.1.dist-info/WHEEL
cameo_txt-0.0.1.dist-info/top_level.txt
cameo_txt-0.0.1.dist-info/RECORD
