Metadata-Version: 2.1
Name: cameo-txt
Version: 0.0.1
Summary: 將各種格式的檔案提取成txt
Author: JcXGTcW
License-File: LICENSE
Requires-Dist: requests (==2.28.2)
Requires-Dist: python-docx (==0.8.11)
Requires-Dist: PyPDF2 (==3.0.1)
Requires-Dist: chardet (==3.0.4)
Requires-Dist: odfpy (==1.4.1)
